dock_r/__init__.py
dock_r/cli.py
dock_r/main.py
dock_r-0.2.1.dist-info/entry_points.txt
dock_r-0.2.1.dist-info/LICENSE
dock_r-0.2.1.dist-info/WHEEL
dock_r-0.2.1.dist-info/METADATA
dock_r-0.2.1.dist-info/RECORD
