Metadata-Version: 2.1
Name: dock-r
Version: 0.2.1
Summary: Tools to go faster with docker.
License: MIT
Author: AJ Steers
Author-email: aj.steers@slalom.com
Requires-Python: >=3.7,<4.0
Classifier: License :: OSI Approved :: MIT License
Classifier: Programming Language :: Python :: 3
Classifier: Programming Language :: Python :: 3.7
Classifier: Programming Language :: Python :: 3.8
Classifier: Programming Language :: Python :: 3.9
Requires-Dist: docker (>=4.4.1,<5.0.0)
Requires-Dist: fire (>=0.4.0,<0.5.0)
Requires-Dist: logless (>=0.2.1,<0.3.0)
Requires-Dist: runnow (>=0.1.0,<0.2.0)
Requires-Dist: uio (>=0.2.0,<0.3.0)
